[{"goals": 0, "successfulDribbles": 1, "tackles": 3, "assists": 0, "accuratePassesPercentage": 83.44, "rating": 6.7, "player": {"name": "Ali Yusuf", "slug": "ali-yusuf", "userCount": 22, "id": 1107439}, "team": {"name": "Libya", "slug": "libya", "shortName": "Libya", "userCount": 0, "type": 0, "id": 4775, "teamColors": {"primary": "#52b030", "secondary": "#52b030", "text": "#ffffff"}}}, {"goals": 0, "successfulDribbles": 2, "tackles": 2, "assists": 0, "accuratePassesPercentage": 76.67, "rating": 6.7, "player": {"name": "Lu\u00eds Asu\u00e9", "slug": "luis-asue", "userCount": 21, "id": 1064103}, "team": {"name": "Equatorial Guinea", "slug": "equatorial-guinea", "shortName": "Equatorial Guinea", "userCount": 0, "type": 0, "id": 8032, "teamColors": {"primary": "#52b030", "secondary": "#52b030", "text": "#ffffff"}}}, {"goals": 0, "successfulDribbles": 1, "tackles": 3, "assists": 0, "accuratePassesPercentage": 89.36, "rating": 6.7, "player": {"name": "Pedro Miguel", "slug": "pedro-miguel", "userCount": 19, "id": 1017970}, "team": {"name": "Angola", "slug": "angola", "shortName": "Angola", "userCount": 0, "type": 0, "id": 4692, "teamColors": {"primary": "#52b030", "secondary": "#52b030", "text": "#ffffff"}}}, {"goals": 0, "successfulDribbles": 1, "tackles": 1, "assists": 0, "accuratePassesPercentage": 83.74, "rating": 6.7, "player": {"name": "Taher Ben Amer", "slug": "taher-ben-amer", "userCount": 19, "id": 1098852}, "team": {"name": "Libya", "slug": "libya", "shortName": "Libya", "userCount": 0, "type": 0, "id": 4775, "teamColors": {"primary": "#52b030", "secondary": "#52b030", "text": "#ffffff"}}}, {"goals": 0, "successfulDribbles": 0, "tackles": 2, "assists": 0, "accuratePassesPercentage": 61.11, "rating": 6.7, "player": {"name": "\u00d3scar Siafa", "slug": "oscar-siafa", "userCount": 17, "id": 1006161}, "team": {"name": "Equatorial Guinea", "slug": "equatorial-guinea", "shortName": "Equatorial Guinea", "userCount": 0, "type": 0, "id": 8032, "teamColors": {"primary": "#52b030", "secondary": "#52b030", "text": "#ffffff"}}}, {"goals": 0, "successfulDribbles": 1, "tackles": 4, "assists": 0, "accuratePassesPercentage": 89.53, "rating": 6.7, "player": {"name": "Mohammed Al Touhami", "slug": "mohammed-al-touhami", "userCount": 8, "id": 1099409}, "team": {"name": "Libya", "slug": "libya", "shortName": "Libya", "userCount": 0, "type": 0, "id": 4775, "teamColors": {"primary": "#52b030", "secondary": "#52b030", "text": "#ffffff"}}}, {"goals": 0, "successfulDribbles": 1, "tackles": 5, "assists": 0, "accuratePassesPercentage": 69.49, "rating": 6.7, "player": {"name": "Aboulqasem Rajab", "slug": "aboulqasem-rajab", "userCount": 8, "id": 1111890}, "team": {"name": "Libya", "slug": "libya", "shortName": "Libya", "userCount": 0, "type": 0, "id": 4775, "teamColors": {"primary": "#52b030", "secondary": "#52b030", "text": "#ffffff"}}}, {"goals": 0, "successfulDribbles": 1, "tackles": 7, "assists": 0, "accuratePassesPercentage": 82.98, "rating": 6.7, "player": {"name": "Frank Onyeka", "slug": "frank-onyeka", "userCount": 773, "id": 885864}, "team": {"name": "Nigeria", "slug": "nigeria", "shortName": "Nigeria", "userCount": 0, "type": 0, "id": 4785, "teamColors": {"primary": "#52b030", "secondary": "#52b030", "text": "#ffffff"}}}, {"goals": 0, "successfulDribbles": 3, "tackles": 7, "assists": 0, "accuratePassesPercentage": 79.14, "rating": 6.7, "player": {"name": "Jose Dembi", "slug": "jose-dembi", "userCount": 40, "id": 864774}, "team": {"name": "Congo Republic", "slug": "congo-republic", "shortName": "Congo Republic", "userCount": 0, "type": 0, "id": 8040, "teamColors": {"primary": "#52b030", "secondary": "#52b030", "text": "#ffffff"}}}, {"goals": 0, "successfulDribbles": 2, "tackles": 8, "assists": 0, "accuratePassesPercentage": 72.97, "rating": 6.7, "player": {"name": "Al-Gozoli Nooh", "slug": "al-gozoli-nooh", "userCount": 12, "id": 1104515}, "team": {"name": "Sudan", "slug": "sudan", "shortName": "Sudan", "userCount": 0, "type": 0, "id": 4734, "teamColors": {"primary": "#52b030", "secondary": "#52b030", "text": "#ffffff"}}}, {"goals": 0, "successfulDribbles": 1, "tackles": 1, "assists": 0, "accuratePassesPercentage": 65.31, "rating": 6.7, "player": {"name": "Micium Mhone", "slug": "micium-mhone", "userCount": 7, "id": 990885}, "team": {"name": "Malawi", "slug": "malawi", "shortName": "Malawi", "userCount": 0, "type": 0, "id": 8043, "teamColors": {"primary": "#52b030", "secondary": "#52b030", "text": "#ffffff"}}}, {"goals": 0, "successfulDribbles": 4, "tackles": 17, "assists": 0, "accuratePassesPercentage": 66.97, "rating": 6.7, "player": {"name": "Alford Velaphi", "slug": "alford-velaphi", "userCount": 1, "id": 990480}, "team": {"name": "Botswana", "slug": "botswana", "shortName": "Botswana", "userCount": 0, "type": 0, "id": 4747, "teamColors": {"primary": "#52b030", "secondary": "#52b030", "text": "#ffffff"}}}, {"goals": 0, "successfulDribbles": 4, "tackles": 6, "assists": 0, "accuratePassesPercentage": 81.37, "rating": 6.7, "player": {"name": "Seydouba Cisse", "slug": "seydouba-cisse", "userCount": 1404, "id": 906065}, "team": {"name": "Guinea", "slug": "guinea", "shortName": "Guinea", "userCount": 0, "type": 0, "id": 4826, "teamColors": {"primary": "#52b030", "secondary": "#52b030", "text": "#ffffff"}}}, {"goals": 0, "successfulDribbles": 0, "tackles": 6, "assists": 0, "accuratePassesPercentage": 80, "rating": 6.7, "player": {"name": "Antoine Conte", "slug": "antoine-conte", "userCount": 474, "id": 149733}, "team": {"name": "Guinea", "slug": "guinea", "shortName": "Guinea", "userCount": 0, "type": 0, "id": 4826, "teamColors": {"primary": "#52b030", "secondary": "#52b030", "text": "#ffffff"}}}, {"goals": 0, "successfulDribbles": 0, "tackles": 1, "assists": 0, "accuratePassesPercentage": 43.7, "rating": 6.7, "player": {"name": "Sekhoane Moerane", "slug": "sekhoane-moerane", "userCount": 12, "id": 1006156}, "team": {"name": "Lesotho", "slug": "lesotho", "shortName": "Lesotho", "userCount": 0, "type": 0, "id": 8033, "teamColors": {"primary": "#52b030", "secondary": "#52b030", "text": "#ffffff"}}}, {"goals": 0, "successfulDribbles": 1, "tackles": 7, "assists": 0, "accuratePassesPercentage": 78.83, "rating": 6.7, "player": {"name": "Thatayaone Ditlhokwe", "slug": "thatayaone-ditlhokwe", "userCount": 35, "id": 990687}, "team": {"name": "Botswana", "slug": "botswana", "shortName": "Botswana", "userCount": 0, "type": 0, "id": 4747, "teamColors": {"primary": "#52b030", "secondary": "#52b030", "text": "#ffffff"}}}, {"goals": 0, "successfulDribbles": 0, "tackles": 2, "assists": 0, "accuratePassesPercentage": 87.5, "rating": 6.7, "player": {"name": "Dion Lopy", "slug": "dion-lopy", "userCount": 1272, "id": 982327}, "team": {"name": "Senegal", "slug": "senegal", "shortName": "Senegal", "userCount": 0, "type": 0, "id": 4739, "teamColors": {"primary": "#52b030", "secondary": "#52b030", "text": "#ffffff"}}}, {"goals": 2, "successfulDribbles": 4, "tackles": 12, "assists": 0, "accuratePassesPercentage": 76.54, "rating": 6.68, "player": {"name": "Chol Daniel", "slug": "chol-daniel", "userCount": 7, "id": 990528}, "team": {"name": "South Sudan", "slug": "south-sudan", "shortName": "South Sudan", "userCount": 0, "type": 0, "id": 88508, "teamColors": {"primary": "#52b030", "secondary": "#52b030", "text": "#ffffff"}}}, {"goals": 0, "successfulDribbles": 0, "tackles": 0, "assists": 0, "accuratePassesPercentage": 67.63, "rating": 6.68, "player": {"name": "Ibrahim Kone", "slug": "ibrahim-kone", "userCount": 401, "id": 47358}, "team": {"name": "Guinea", "slug": "guinea", "shortName": "Guinea", "userCount": 0, "type": 0, "id": 4826, "teamColors": {"primary": "#52b030", "secondary": "#52b030", "text": "#ffffff"}}}, {"goals": 0, "successfulDribbles": 5, "tackles": 2, "assists": 0, "accuratePassesPercentage": 79.66, "rating": 6.68, "player": {"name": "Ange Mutsinzi", "slug": "ange-mutsinzi", "userCount": 20, "id": 948342}, "team": {"name": "Rwanda", "slug": "rwanda", "shortName": "Rwanda", "userCount": 0, "type": 0, "id": 8037, "teamColors": {"primary": "#52b030", "secondary": "#52b030", "text": "#ffffff"}}}]