[{"goals": 1, "expectedGoals": 1.06, "successfulDribbles": 4, "tackles": 2, "assists": 2, "accuratePassesPercentage": 72.73, "rating": 7.2, "player": {"name": "Christian Puli\u0161i\u0107", "slug": "christian-pulisic", "userCount": 22141, "id": 817957}, "team": {"name": "USA", "slug": "usa", "shortName": "USA", "userCount": 0, "type": 0, "id": 4724, "teamColors": {"primary": "#52b030", "secondary": "#52b030", "text": "#ffffff"}}}, {"goals": 1, "expectedGoals": 1.14, "successfulDribbles": 2, "tackles": 3, "assists": 0, "accuratePassesPercentage": 89.82, "rating": 7.2, "player": {"name": "\u0130lkay G\u00fcndo\u011fan", "slug": "ilkay-gundogan", "userCount": 30289, "id": 45853}, "team": {"name": "Germany", "slug": "germany", "shortName": "Germany", "userCount": 0, "type": 0, "id": 4711, "teamColors": {"primary": "#52b030", "secondary": "#52b030", "text": "#ffffff"}}}, {"goals": 0, "expectedGoals": 0.06, "successfulDribbles": 0, "tackles": 5, "assists": 2, "accuratePassesPercentage": 83.1, "rating": 7.2, "player": {"name": "Andrija \u017divkovi\u0107", "slug": "andrija-zivkovic", "userCount": 1717, "id": 188133}, "team": {"name": "Serbia", "slug": "serbia", "shortName": "Serbia", "userCount": 0, "type": 0, "id": 6355, "teamColors": {"primary": "#52b030", "secondary": "#52b030", "text": "#ffffff"}}}, {"goals": 0, "expectedGoals": 0, "successfulDribbles": 0, "tackles": 4, "assists": 1, "accuratePassesPercentage": 91.51, "rating": 7.2, "player": {"name": "Toby Alderweireld", "slug": "toby-alderweireld", "userCount": 2209, "id": 44575}, "team": {"name": "Belgium", "slug": "belgium", "shortName": "Belgium", "userCount": 0, "type": 0, "id": 4717, "teamColors": {"primary": "#52b030", "secondary": "#52b030", "text": "#ffffff"}}}, {"goals": 0, "expectedGoals": 0.23, "successfulDribbles": 4, "tackles": 1, "assists": 0, "accuratePassesPercentage": 73.21, "rating": 7.2, "player": {"name": "Kevin De Bruyne", "slug": "kevin-de-bruyne", "userCount": 140538, "id": 70996}, "team": {"name": "Belgium", "slug": "belgium", "shortName": "Belgium", "userCount": 0, "type": 0, "id": 4717, "teamColors": {"primary": "#52b030", "secondary": "#52b030", "text": "#ffffff"}}}, {"goals": 0, "expectedGoals": 0.03, "successfulDribbles": 1, "tackles": 8, "assists": 0, "accuratePassesPercentage": 91.61, "rating": 7.2, "player": {"name": "Alex Sandro", "slug": "alex-sandro", "userCount": 5111, "id": 84854}, "team": {"name": "Brazil", "slug": "brazil", "shortName": "Brazil", "userCount": 0, "type": 0, "id": 4748, "teamColors": {"primary": "#52b030", "secondary": "#52b030", "text": "#ffffff"}}}, {"goals": 0, "expectedGoals": 0, "successfulDribbles": 0, "tackles": 6, "assists": 0, "accuratePassesPercentage": 79.17, "rating": 7.2, "player": {"name": "Thilo Kehrer", "slug": "thilo-kehrer", "userCount": 1928, "id": 281277}, "team": {"name": "Germany", "slug": "germany", "shortName": "Germany", "userCount": 0, "type": 0, "id": 4711, "teamColors": {"primary": "#52b030", "secondary": "#52b030", "text": "#ffffff"}}}, {"goals": 1, "expectedGoals": 0.64, "successfulDribbles": 13, "tackles": 3, "assists": 1, "accuratePassesPercentage": 87.68, "rating": 7.18, "player": {"name": "\u00c1ngel Di Mar\u00eda", "slug": "angel-di-maria", "userCount": 57996, "id": 30027}, "team": {"name": "Argentina", "slug": "argentina", "shortName": "Argentina", "userCount": 0, "type": 0, "id": 4819, "teamColors": {"primary": "#52b030", "secondary": "#52b030", "text": "#ffffff"}}}, {"goals": 3, "expectedGoals": 1.36, "successfulDribbles": 1, "tackles": 1, "assists": 1, "accuratePassesPercentage": 68.29, "rating": 7.18, "player": {"name": "\u00c1lvaro Morata", "slug": "alvaro-morata", "userCount": 15230, "id": 125407}, "team": {"name": "Spain", "slug": "spain", "shortName": "Spain", "userCount": 0, "type": 0, "id": 4698, "teamColors": {"primary": "#52b030", "secondary": "#52b030", "text": "#ffffff"}}}, {"goals": 1, "expectedGoals": 0.43, "successfulDribbles": 2, "tackles": 3, "assists": 2, "accuratePassesPercentage": 88.36, "rating": 7.18, "player": {"name": "Rapha\u00ebl Guerreiro", "slug": "raphael-guerreiro", "userCount": 4622, "id": 246999}, "team": {"name": "Portugal", "slug": "portugal", "shortName": "Portugal", "userCount": 0, "type": 0, "id": 4704, "teamColors": {"primary": "#52b030", "secondary": "#52b030", "text": "#ffffff"}}}, {"goals": 2, "expectedGoals": 2.19, "successfulDribbles": 1, "tackles": 0, "assists": 1, "accuratePassesPercentage": 62.5, "rating": 7.17, "player": {"name": "Niclas F\u00fcllkrug", "slug": "niclas-fullkrug", "userCount": 3629, "id": 132645}, "team": {"name": "Germany", "slug": "germany", "shortName": "Germany", "userCount": 0, "type": 0, "id": 4711, "teamColors": {"primary": "#52b030", "secondary": "#52b030", "text": "#ffffff"}}}, {"goals": 2, "expectedGoals": 0.19, "successfulDribbles": 0, "tackles": 0, "assists": 0, "accuratePassesPercentage": 60, "rating": 7.17, "player": {"name": "Wout Weghorst", "slug": "wout-weghorst", "userCount": 8096, "id": 252215}, "team": {"name": "Netherlands", "slug": "netherlands", "shortName": "Netherlands", "userCount": 0, "type": 0, "id": 4705, "teamColors": {"primary": "#52b030", "secondary": "#52b030", "text": "#ffffff"}}}, {"goals": 0, "expectedGoals": 0.07, "successfulDribbles": 1, "tackles": 10, "assists": 0, "accuratePassesPercentage": 87.1, "rating": 7.17, "player": {"name": "Ellyes Skhiri", "slug": "ellyes-skhiri", "userCount": 3742, "id": 591706}, "team": {"name": "Tunisia", "slug": "tunisia", "shortName": "Tunisia", "userCount": 0, "type": 0, "id": 4729, "teamColors": {"primary": "#52b030", "secondary": "#52b030", "text": "#ffffff"}}}, {"goals": 1, "expectedGoals": 0.14, "successfulDribbles": 1, "tackles": 9, "assists": 0, "accuratePassesPercentage": 89.9, "rating": 7.16, "player": {"name": "Jo\u0161ko Gvardiol", "slug": "josko-gvardiol", "userCount": 18518, "id": 964994}, "team": {"name": "Croatia", "slug": "croatia", "shortName": "Croatia", "userCount": 0, "type": 0, "id": 4715, "teamColors": {"primary": "#52b030", "secondary": "#52b030", "text": "#ffffff"}}}, {"goals": 1, "expectedGoals": 0.27, "successfulDribbles": 1, "tackles": 7, "assists": 0, "accuratePassesPercentage": 74.03, "rating": 7.15, "player": {"name": "Ramin Rezaeian", "slug": "ramin-rezaeian", "userCount": 724, "id": 786133}, "team": {"name": "Iran", "slug": "iran", "shortName": "Iran", "userCount": 0, "type": 0, "id": 4766, "teamColors": {"primary": "#52b030", "secondary": "#52b030", "text": "#ffffff"}}}, {"goals": 1, "expectedGoals": 1.04, "successfulDribbles": 2, "tackles": 12, "assists": 1, "accuratePassesPercentage": 85.04, "rating": 7.13, "player": {"name": "Adrien Rabiot", "slug": "adrien-rabiot", "userCount": 6407, "id": 250737}, "team": {"name": "France", "slug": "france", "shortName": "France", "userCount": 0, "type": 0, "id": 4481, "teamColors": {"primary": "#52b030", "secondary": "#52b030", "text": "#ffffff"}}}, {"goals": 0, "expectedGoals": 0.03, "successfulDribbles": 1, "tackles": 12, "assists": 1, "accuratePassesPercentage": 83.86, "rating": 7.13, "player": {"name": "Josip Juranovi\u0107", "slug": "josip-juranovic", "userCount": 3586, "id": 791642}, "team": {"name": "Croatia", "slug": "croatia", "shortName": "Croatia", "userCount": 0, "type": 0, "id": 4715, "teamColors": {"primary": "#52b030", "secondary": "#52b030", "text": "#ffffff"}}}, {"goals": 0, "expectedGoals": 0.02, "successfulDribbles": 0, "tackles": 2, "assists": 0, "accuratePassesPercentage": 86.13, "rating": 7.13, "player": {"name": "Montassar Talbi", "slug": "montassar-talbi", "userCount": 2365, "id": 879618}, "team": {"name": "Tunisia", "slug": "tunisia", "shortName": "Tunisia", "userCount": 0, "type": 0, "id": 4729, "teamColors": {"primary": "#52b030", "secondary": "#52b030", "text": "#ffffff"}}}, {"goals": 0, "expectedGoals": 0.32, "successfulDribbles": 11, "tackles": 24, "assists": 0, "accuratePassesPercentage": 90.79, "rating": 7.13, "player": {"name": "Mateo Kova\u010di\u0107", "slug": "mateo-kovacic", "userCount": 16264, "id": 136710}, "team": {"name": "Croatia", "slug": "croatia", "shortName": "Croatia", "userCount": 0, "type": 0, "id": 4715, "teamColors": {"primary": "#52b030", "secondary": "#52b030", "text": "#ffffff"}}}, {"goals": 1, "expectedGoals": 0.49, "successfulDribbles": 1, "tackles": 5, "assists": 0, "accuratePassesPercentage": 83.79, "rating": 7.13, "player": {"name": "Pepe", "slug": "pepe", "userCount": 6293, "id": 5884}, "team": {"name": "Portugal", "slug": "portugal", "shortName": "Portugal", "userCount": 0, "type": 0, "id": 4704, "teamColors": {"primary": "#52b030", "secondary": "#52b030", "text": "#ffffff"}}}]